pysigmap/__init__.py
pysigmap/bilog.py
pysigmap/boone.py
pysigmap/casagrande.py
pysigmap/data.py
pysigmap/energy.py
pysigmap/pachecosilva.py
pysigmap-0.1.10.dist-info/LICENSE
pysigmap-0.1.10.dist-info/WHEEL
pysigmap-0.1.10.dist-info/METADATA
pysigmap-0.1.10.dist-info/RECORD
