Metadata-Version: 2.1
Name: pysigmap
Version: 0.1.10
Summary: Application software for calculating the preconsolidation pressure from the incremental loading oedometer testing
Author-email: "Exneyder A. Montoya-Araque" <eamontoyaa@gmail.com>, "A. J. Aparicio-Ortube" <aaparicioo@unal.edu.co>, "D. G. Zapata-Medina" <dgzapata@unal.edu.co>, "L. G. Arboleda-Monsalve" <luis.arboleda@ucf.edu>
Requires-Python: >=3.7
Classifier: License :: OSI Approved :: MIT License
Requires-Dist: numpy >=1.23.5
Requires-Dist: matplotlib >=3.7.1
Requires-Dist: scipy >= 1.11.3
Requires-Dist: pandas >= 1.5.3
Requires-Dist: mstools >= 0.1.0
Project-URL: Documentation, https://pysigmap.readthedocs.io/en/latest/
Project-URL: Source, https://github.com/eamontoyaa/pysigmap
